captcha/__init__.py
captcha/apps.py
captcha/checks.py
captcha/client.py
captcha/constants.py
captcha/fields.py
captcha/models.py
captcha/widgets.py
captcha/templates/captcha/widget_v2_checkbox.html
captcha/templates/captcha/widget_v2_invisible.html
captcha/templates/captcha/widget_v3.html
captcha/templates/captcha/includes/js_v2_checkbox.html
captcha/templates/captcha/includes/js_v2_invisible.html
captcha/templates/captcha/includes/js_v3.html
captcha/tests/__init__.py
captcha/tests/test_client.py
captcha/tests/test_fields.py
captcha/tests/tests.py
captcha/tests/settings/__init__.py
captcha/tests/settings/coveralls_settings.py
django_recaptcha429-2.1.0.dist-info/AUTHORS.rst
django_recaptcha429-2.1.0.dist-info/LICENSE
django_recaptcha429-2.1.0.dist-info/METADATA
django_recaptcha429-2.1.0.dist-info/WHEEL
django_recaptcha429-2.1.0.dist-info/top_level.txt
django_recaptcha429-2.1.0.dist-info/RECORD
