Metadata-Version: 2.1
Name: django-recaptcha429
Version: 2.1.0
Summary: Django recaptcha form field/widget app.
Home-page: http://github.com/Andrew-Chen-Wang/django-recaptcha429
Author: Andrew Chen Wang
Author-email: acwangpython@gmail.com
License: BSD
Keywords: django,reCAPTCHA,reCAPTCHA v2,reCAPTCHA v3
Platform: UNKNOWN
Classifier: Development Status :: 5 - Production/Stable
Classifier: Framework :: Django
Classifier: Framework :: Django :: 2.2
Classifier: Framework :: Django :: 3.2
Classifier: Framework :: Django :: 4.0
Classifier: Intended Audience :: Developers
Classifier: License :: OSI Approved :: BSD License
Classifier: Operating System :: OS Independent
Classifier: Programming Language :: Python
Classifier: Topic :: Internet :: WWW/HTTP :: Dynamic Content
Classifier: Programming Language :: Python :: 3
Classifier: Programming Language :: Python :: 3.7
Classifier: Programming Language :: Python :: 3.8
Classifier: Programming Language :: Python :: 3.9
Classifier: Programming Language :: Python :: 3.10
License-File: LICENSE
License-File: AUTHORS.rst
Requires-Dist: django
